ZTF/PID.py
ZTF/README.md
ZTF/ZTF.py
ZTF/__init__.py
ZTF/version
ZTF-0.0.2.dist-info/LICENSE
ZTF-0.0.2.dist-info/METADATA
ZTF-0.0.2.dist-info/WHEEL
ZTF-0.0.2.dist-info/top_level.txt
ZTF-0.0.2.dist-info/RECORD
